wgan_pytorch/__init__.py
wgan_pytorch/model.py
wgan_pytorch/utils.py
wgan_pytorch-0.1.2.dist-info/LICENSE.md
wgan_pytorch-0.1.2.dist-info/METADATA
wgan_pytorch-0.1.2.dist-info/WHEEL
wgan_pytorch-0.1.2.dist-info/top_level.txt
wgan_pytorch-0.1.2.dist-info/RECORD
