Metadata-Version: 2.1
Name: wgan-pytorch
Version: 0.1.2
Summary: This is a new alogorithm named WGAN, an alternative to traditional GAN training!
Home-page: https://github.com/Lornatang/WassersteinGAN-PyTorch
Author: Liu Changyu
Author-email: liuchangyu1111@gmail.com
License: Apache
Platform: UNKNOWN
Classifier: License :: OSI Approved :: Apache Software License
Classifier: Programming Language :: Python
Classifier: Programming Language :: Python :: 3
Classifier: Programming Language :: Python :: 3.7
Requires-Python: >=3.5.0
Requires-Dist: torch
